dspy_coding_agent_lms/__init__.py
dspy_coding_agent_lms/auth.py
dspy_coding_agent_lms/cache.py
dspy_coding_agent_lms/cli.py
dspy_coding_agent_lms/config.py
dspy_coding_agent_lms/exceptions.py
dspy_coding_agent_lms/lm.py
dspy_coding_agent_lms/response.py
dspy_coding_agent_lms/transcript.py
dspy_coding_agent_lms-0.1.3.dist-info/METADATA
dspy_coding_agent_lms-0.1.3.dist-info/WHEEL
dspy_coding_agent_lms-0.1.3.dist-info/licenses/LICENSE
dspy_coding_agent_lms-0.1.3.dist-info/RECORD
