Metadata-Version: 2.4
Name: dspy-coding-agent-lms
Version: 0.1.3
Summary: DSPy LM integration for Claude Code CLI - route DSPy requests through local Claude Code agent
Project-URL: Homepage, https://github.com/saurabhdas/dspy-coding-agent-lms
Project-URL: Documentation, https://github.com/saurabhdas/dspy-coding-agent-lms#readme
Project-URL: Repository, https://github.com/saurabhdas/dspy-coding-agent-lms
Project-URL: Issues, https://github.com/saurabhdas/dspy-coding-agent-lms/issues
Author: DSPy Coding Agent LMs Contributors
License: MIT
License-File: LICENSE
Keywords: agents,ai,claude,claude-code,coding-agent,dspy,llm
Classifier: Development Status :: 3 - Alpha
Classifier: Intended Audience :: Developers
Classifier: License :: OSI Approved :: MIT License
Classifier: Programming Language :: Python :: 3
Classifier: Programming Language :: Python :: 3.11
Classifier: Programming Language :: Python :: 3.12
Classifier: Programming Language :: Python :: 3.13
Classifier: Topic :: Scientific/Engineering :: Artificial Intelligence
Classifier: Typing :: Typed
Requires-Python: >=3.11
Requires-Dist: dspy>=2.5.0
Provides-Extra: dev
Requires-Dist: mypy>=1.10; extra == 'dev'
Requires-Dist: pytest-asyncio>=0.23; extra == 'dev'
Requires-Dist: pytest-cov>=5.0; extra == 'dev'
Requires-Dist: pytest-mock>=3.14; extra == 'dev'
Requires-Dist: pytest>=8.0; extra == 'dev'
Requires-Dist: ruff>=0.4; extra == 'dev'
